httplite/__init__.py
httplite/http_client.py
httplite-0.0.2.dist-info/LICENSE
httplite-0.0.2.dist-info/METADATA
httplite-0.0.2.dist-info/WHEEL
httplite-0.0.2.dist-info/top_level.txt
httplite-0.0.2.dist-info/RECORD
